forkqueue.py
forkqueue-1.3.dist-info/LICENSE.txt
forkqueue-1.3.dist-info/METADATA
forkqueue-1.3.dist-info/WHEEL
forkqueue-1.3.dist-info/top_level.txt
forkqueue-1.3.dist-info/RECORD
