Metadata-Version: 2.1
Name: forkqueue
Version: 1.3
Summary: Process tasks from a queue using forked processes
Home-page: https://github.com/jeremysanders/forkqueue
Author: Jeremy Sanders
Author-email: jeremy@jeremysanders.net
License: MIT
Project-URL: Source, https://github.com/jeremysanders/forkqueue
Project-URL: Tracker, https://github.com/jeremysanders/forkqueue/issues
Platform: UNKNOWN
Classifier: Development Status :: 4 - Beta
Classifier: Intended Audience :: Developers
Classifier: License :: OSI Approved :: MIT License
Classifier: Programming Language :: Python :: 3.3
Classifier: Programming Language :: Python :: 3.4
Classifier: Programming Language :: Python :: 3.5
Classifier: Programming Language :: Python :: 3.6
Classifier: Programming Language :: Python :: 3.7
Classifier: Programming Language :: Python :: 3.8
Classifier: Programming Language :: Python :: 3.9
Classifier: Programming Language :: Python :: 3.10
Requires-Python: ~=3.3
